django_mpesapy-0.1.2.dist-info/DESCRIPTION.rst
django_mpesapy-0.1.2.dist-info/METADATA
django_mpesapy-0.1.2.dist-info/RECORD
django_mpesapy-0.1.2.dist-info/WHEEL
django_mpesapy-0.1.2.dist-info/metadata.json
django_mpesapy-0.1.2.dist-info/top_level.txt
mpesapy/__init__.py
mpesapy/admin.py
mpesapy/models.py
mpesapy/urls.py
mpesapy/views.py
