Metadata-Version: 1.1
Name: django-mpesapy
Version: 0.1.2
Summary: Django app consuming M-Pesa APIs
Home-page: http://http://pythonhosted.org/django-mpesapy/
Author: James Wanderi
Author-email: wanderi@wanderi.me
License: MIT License
Platform: UNKNOWN
Classifier: Environment :: Web Environment
Classifier: Framework :: Django
Classifier: Development Status :: 5 - Production/Stable
Classifier: Natural Language :: English
Classifier: Intended Audience :: Developers
Classifier: License :: OSI Approved :: MIT License
Classifier: Operating System :: OS Independent
Classifier: Programming Language :: Python
Classifier: Programming Language :: Python :: 2.7
Classifier: Programming Language :: Python :: Implementation :: PyPy
Classifier: Topic :: Software Development :: Libraries :: Python Modules
